{
  "segment_id": "real1_seg001410_001",
  "split": "train",
  "video": "real1",
  "frame_start": 1425,
  "frame_end": 1438,
  "frames": [
    1425,
    1426,
    1427,
    1428,
    1429,
    1430,
    1431,
    1432,
    1433,
    1434,
    1435,
    1436,
    1437,
    1438
  ],
  "actions": [
    "ClippingTissue",
    "CuttingTissue",
    "PullingSeminalVesicle",
    "SuckingBlood"
  ],
  "tools": [
    "clip_applier",
    "grasper",
    "monopolar_scissors",
    "suction_irrigator"
  ],
  "tissues": [
    "blood",
    "generic_tissue",
    "seminal_vesicle"
  ],
  "events": [
    "bleeding"
  ],
  "phase": "vas_deferens_seminal_vesicle_dissection",
  "phase_ambiguous": false,
  "phase_candidates": [
    "vas_deferens_seminal_vesicle_dissection"
  ],
  "unknown_actions": []
}