{
  "segment_id": "real1_seg006916_000",
  "split": "train",
  "video": "real1",
  "frame_start": 6916,
  "frame_end": 6925,
  "frames": [
    6916,
    6917,
    6918,
    6919,
    6920,
    6921,
    6922,
    6923,
    6924,
    6925
  ],
  "actions": [
    "BladderAnastomosis"
  ],
  "tools": [
    "needle_driver"
  ],
  "tissues": [
    "bladder"
  ],
  "events": [],
  "phase": "bladder_anastomosis",
  "phase_ambiguous": false,
  "phase_candidates": [
    "bladder_anastomosis"
  ],
  "unknown_actions": []
}