{
  "segment_id": "real1_seg005320_000",
  "split": "train",
  "video": "real1",
  "frame_start": 5320,
  "frame_end": 5331,
  "frames": [
    5320,
    5321,
    5322,
    5323,
    5324,
    5325,
    5326,
    5327,
    5328,
    5329,
    5330,
    5331
  ],
  "actions": [
    "PullingBladderNeck"
  ],
  "tools": [
    "grasper"
  ],
  "tissues": [
    "bladder_neck"
  ],
  "events": [],
  "phase": "bladder_neck_dissection",
  "phase_ambiguous": false,
  "phase_candidates": [
    "bladder_neck_dissection"
  ],
  "unknown_actions": []
}