{
  "segment_id": "real1_seg002740_000",
  "split": "train",
  "video": "real1",
  "frame_start": 2740,
  "frame_end": 2752,
  "frames": [
    2740,
    2741,
    2742,
    2743,
    2744,
    2745,
    2746,
    2747,
    2748,
    2749,
    2750,
    2751,
    2752
  ],
  "actions": [
    "ClippingTissue",
    "CuttingTissue",
    "PullingTissue"
  ],
  "tools": [
    "clip_applier",
    "grasper",
    "monopolar_scissors"
  ],
  "tissues": [
    "generic_tissue"
  ],
  "events": [],
  "phase": null,
  "phase_ambiguous": false,
  "phase_candidates": [],
  "unknown_actions": []
}