{
  "segment_id": "real1_seg005224_000",
  "split": "train",
  "video": "real1",
  "frame_start": 5224,
  "frame_end": 5233,
  "frames": [
    5224,
    5225,
    5226,
    5227,
    5228,
    5229,
    5230,
    5231,
    5232,
    5233
  ],
  "actions": [
    "CuttingProstate",
    "PullingProstate",
    "SuckingBlood"
  ],
  "tools": [
    "grasper",
    "monopolar_scissors",
    "suction_irrigator"
  ],
  "tissues": [
    "blood",
    "prostate"
  ],
  "events": [
    "bleeding"
  ],
  "phase": "prostate_dissection",
  "phase_ambiguous": false,
  "phase_candidates": [
    "prostate_dissection"
  ],
  "unknown_actions": []
}