{
  "segment_id": "real2_seg006365_000",
  "split": "train",
  "video": "real2",
  "frame_start": 6365,
  "frame_end": 6371,
  "frames": [
    6365,
    6366,
    6367,
    6368,
    6369,
    6370,
    6371
  ],
  "actions": [
    "CuttingProstate",
    "PullingSeminalVesicle",
    "SuckingBlood"
  ],
  "tools": [
    "grasper",
    "monopolar_scissors",
    "suction_irrigator"
  ],
  "tissues": [
    "blood",
    "prostate",
    "seminal_vesicle"
  ],
  "events": [
    "bleeding"
  ],
  "phase": "prostate_dissection",
  "phase_ambiguous": true,
  "phase_candidates": [
    "prostate_dissection",
    "vas_deferens_seminal_vesicle_dissection"
  ],
  "unknown_actions": []
}