{
  "segment_id": "real2_seg005073_000",
  "split": "train",
  "video": "real2",
  "frame_start": 5073,
  "frame_end": 5084,
  "frames": [
    5073,
    5074,
    5075,
    5076,
    5077,
    5078,
    5079,
    5080,
    5081,
    5082,
    5083,
    5084
  ],
  "actions": [
    "PullingTissue",
    "SuckingBlood"
  ],
  "tools": [
    "grasper",
    "suction_irrigator"
  ],
  "tissues": [
    "blood",
    "generic_tissue"
  ],
  "events": [
    "bleeding"
  ],
  "phase": null,
  "phase_ambiguous": false,
  "phase_candidates": [],
  "unknown_actions": []
}