{
  "segment_id": "real4_seg011133_005",
  "split": "train",
  "video": "real4",
  "frame_start": 11208,
  "frame_end": 11222,
  "frames": [
    11208,
    11209,
    11210,
    11211,
    11212,
    11213,
    11214,
    11215,
    11216,
    11217,
    11218,
    11219,
    11220,
    11221,
    11222
  ],
  "actions": [
    "SuckingBlood"
  ],
  "tools": [
    "suction_irrigator"
  ],
  "tissues": [
    "blood"
  ],
  "events": [
    "bleeding"
  ],
  "phase": null,
  "phase_ambiguous": false,
  "phase_candidates": [],
  "unknown_actions": []
}