{
  "segment_id": "real4_seg008269_006",
  "split": "train",
  "video": "real4",
  "frame_start": 8359,
  "frame_end": 8373,
  "frames": [
    8359,
    8360,
    8361,
    8362,
    8363,
    8364,
    8365,
    8366,
    8367,
    8368,
    8369,
    8370,
    8371,
    8372,
    8373
  ],
  "actions": [
    "CuttingTissue",
    "PullingTissue"
  ],
  "tools": [
    "grasper",
    "monopolar_scissors"
  ],
  "tissues": [
    "generic_tissue"
  ],
  "events": [],
  "phase": null,
  "phase_ambiguous": false,
  "phase_candidates": [],
  "unknown_actions": []
}