{
  "segment_id": "real4_seg022981_005",
  "split": "train",
  "video": "real4",
  "frame_start": 23056,
  "frame_end": 23070,
  "frames": [
    23056,
    23057,
    23058,
    23059,
    23060,
    23061,
    23062,
    23063,
    23064,
    23065,
    23066,
    23067,
    23068,
    23069,
    23070
  ],
  "actions": [
    "CuttingSeminalVesicle",
    "PullingSeminalVesicle"
  ],
  "tools": [
    "grasper",
    "monopolar_scissors"
  ],
  "tissues": [
    "seminal_vesicle"
  ],
  "events": [],
  "phase": "vas_deferens_seminal_vesicle_dissection",
  "phase_ambiguous": false,
  "phase_candidates": [
    "vas_deferens_seminal_vesicle_dissection"
  ],
  "unknown_actions": []
}