{
  "segment_id": "real4_seg017657_000",
  "split": "train",
  "video": "real4",
  "frame_start": 17657,
  "frame_end": 17667,
  "frames": [
    17657,
    17658,
    17659,
    17660,
    17661,
    17662,
    17663,
    17664,
    17665,
    17666,
    17667
  ],
  "actions": [
    "SuckingBlood"
  ],
  "tools": [
    "suction_irrigator"
  ],
  "tissues": [
    "blood"
  ],
  "events": [
    "bleeding"
  ],
  "phase": null,
  "phase_ambiguous": false,
  "phase_candidates": [],
  "unknown_actions": []
}