{
  "segment_id": "real4_seg005038_003",
  "split": "train",
  "video": "real4",
  "frame_start": 5083,
  "frame_end": 5097,
  "frames": [
    5083,
    5084,
    5085,
    5086,
    5087,
    5088,
    5089,
    5090,
    5091,
    5092,
    5093,
    5094,
    5095,
    5096,
    5097
  ],
  "actions": [
    "CuttingSeminalVesicle",
    "PullingSeminalVesicle"
  ],
  "tools": [
    "grasper",
    "monopolar_scissors"
  ],
  "tissues": [
    "seminal_vesicle"
  ],
  "events": [],
  "phase": "vas_deferens_seminal_vesicle_dissection",
  "phase_ambiguous": false,
  "phase_candidates": [
    "vas_deferens_seminal_vesicle_dissection"
  ],
  "unknown_actions": []
}