{
  "segment_id": "real4_seg026992_010",
  "split": "train",
  "video": "real4",
  "frame_start": 27142,
  "frame_end": 27156,
  "frames": [
    27142,
    27143,
    27144,
    27145,
    27146,
    27147,
    27148,
    27149,
    27150,
    27151,
    27152,
    27153,
    27154,
    27155,
    27156
  ],
  "actions": [
    "BladderAnastomosis"
  ],
  "tools": [
    "needle_driver"
  ],
  "tissues": [
    "bladder"
  ],
  "events": [],
  "phase": "bladder_anastomosis",
  "phase_ambiguous": false,
  "phase_candidates": [
    "bladder_anastomosis"
  ],
  "unknown_actions": []
}