{
  "segment_id": "real4_seg003059_005",
  "split": "train",
  "video": "real4",
  "frame_start": 3134,
  "frame_end": 3148,
  "frames": [
    3134,
    3135,
    3136,
    3137,
    3138,
    3139,
    3140,
    3141,
    3142,
    3143,
    3144,
    3145,
    3146,
    3147,
    3148
  ],
  "actions": [
    "CuttingTissue",
    "PullingVasDeferens"
  ],
  "tools": [
    "grasper",
    "monopolar_scissors"
  ],
  "tissues": [
    "generic_tissue",
    "vas_deferens"
  ],
  "events": [],
  "phase": "vas_deferens_seminal_vesicle_dissection",
  "phase_ambiguous": false,
  "phase_candidates": [
    "vas_deferens_seminal_vesicle_dissection"
  ],
  "unknown_actions": []
}